{
  "data": [
    {
      "id": "1",
      "eventname": "event 1",
      "startdate": "2024-04-15",
      "enddate": "2024-04-17",
      "location": "location 1"
    },
    {
      "id": "2",
      "eventname": "event 2",
      "startdate": "2024-05-20",
      "enddate": "2024-05-22",
      "location": "location 2"
    },
    {
      "id": "3",
      "eventname": "event 3",
      "startdate": "2024-06-10",
      "enddate": "2024-06-12",
      "location": "location 3"
    },
    {
      "id": "4",
      "eventname": "event 4",
      "startdate": "2024-07-05",
      "enddate": "2024-07-07",
      "location": "location 4"
    },
    {
      "id": "5",
      "eventname": "event 5",
      "startdate": "2024-08-12",
      "enddate": "2024-08-14",
      "location": "location 5"
    }
  ]
}
